scgraphne/__init__.py
scgraphne/run_scgraphne.py
scgraphne/data/__init__.py
scgraphne/data/data_utils.py
scgraphne/data/graph.py
scgraphne/model/__init__.py
scgraphne/model/decoder.py
scgraphne/model/scgraphne.py
scgraphne/utils/__init__.py
scgraphne/utils/metric.py
scgraphne/utils/read.py
scgraphne/utils/utils.py
scgraphne-0.1.1.dist-info/LICENSE
scgraphne-0.1.1.dist-info/METADATA
scgraphne-0.1.1.dist-info/WHEEL
scgraphne-0.1.1.dist-info/top_level.txt
scgraphne-0.1.1.dist-info/RECORD
