Metadata-Version: 2.1
Name: scgraphne
Version: 0.1.1
Summary: scGraphNE: a novel scRNA-seq representation learning method based on graph node embedding
Home-page: https://github.com/sldyns/scGraphNE
Author: Kun Qian, Ting Li
Author-email: kun_qian@foxmail.com
Maintainer: Kun Qian
Maintainer-email: kun_qian@foxmail.com
License: MIT Licence
Keywords: single-cell RNA-sequencing,Graph node embedding,Dimensionality reduction
Platform: any
Requires-Dist: numpy
Requires-Dist: scanpy
Requires-Dist: h5py
Requires-Dist: torch
Requires-Dist: dgl
Requires-Dist: pandas
Requires-Dist: scipy
Requires-Dist: sklearn
